{
  "url": "https://redtreewebdesign.com/",
  "requestedUrl": "https://redtreewebdesign.com/",
  "timestamp": 1704776596356,
  "ranks": {
    "hundos": 7,
    "performance": 8,
    "accessibility": 3,
    "cumulative": 7
  },
  "lighthouse": {
    "version": "11.4.0",
    "performance": 0.68,
    "accessibility": 0.92,
    "bestPractices": 0.78,
    "seo": 0.93,
    "total": 331
  },
  "firstContentfulPaint": 2694.8561,
  "firstMeaningfulPaint": 2694.8561,
  "speedIndex": 4303.855629324751,
  "largestContentfulPaint": 9146.2144,
  "totalBlockingTime": 102.5,
  "cumulativeLayoutShift": 0.00005555803451670466,
  "timeToInteractive": 8965.30035,
  "maxPotentialFirstInputDelay": 154,
  "timeToFirstByte": 154.936,
  "weight": {
    "summary": "54 requests • 1.1 MiB",
    "total": 1105677,
    "image": 180873,
    "imageCount": 8,
    "script": 577971,
    "scriptCount": 15,
    "document": 16832,
    "font": 184207,
    "fontCount": 4,
    "stylesheet": 161777,
    "stylesheetCount": 18,
    "thirdParty": 662605,
    "thirdPartyCount": 8
  },
  "run": {
    "number": 1,
    "total": 1
  },
  "sidequests": {
    "-weight.total": 3,
    "+weight.total": 22,
    "-weight.document": 7,
    "+weight.document": 18,
    "-weight.script": 10,
    "+weight.script": 15,
    "-weight.image": 5,
    "+weight.image": 20,
    "-weight.font": 11,
    "+weight.font": 13,
    "+weight.fontCount": 9,
    "-timeToFirstByte": 14,
    "-totalBlockingTime": 7,
    "-largestContentfulPaint": 11
  },
  "axe": {
    "passes": 787,
    "violations": 7
  }
}